diffcrysgen/__init__.py
diffcrysgen/analyze_generated_structures.py
diffcrysgen/invert_pcr.py
diffcrysgen/model.py
diffcrysgen/sampler.py
diffcrysgen/trainer.py
diffcrysgen/utils.py
diffcrysgen-0.1.0.dist-info/licenses/LICENSE
diffcrysgen-0.1.0.dist-info/METADATA
diffcrysgen-0.1.0.dist-info/WHEEL
diffcrysgen-0.1.0.dist-info/top_level.txt
diffcrysgen-0.1.0.dist-info/RECORD
