Metadata-Version: 2.4
Name: diffcrysgen
Version: 0.1.0
Summary: "DiffCrysGen is a score-based diffusion model for accelerated design of diverse inorganic crystalline materials."
Home-page: https://github.com/SouravMal/DiffCrysGen.git
Classifier: Programming Language :: Python :: 3
Classifier: Programming Language :: Python :: 3.11
Classifier: License :: OSI Approved :: MIT License
Classifier: Operating System :: OS Independent
Classifier: Development Status :: 3 - Alpha
Classifier: Topic :: Scientific/Engineering :: Chemistry
Classifier: Topic :: Scientific/Engineering :: Physics
Requires-Python: >=3.11
License-File: LICENSE
Requires-Dist: torch~=2.5.1
Requires-Dist: numpy~=2.0.1
Requires-Dist: pandas~=2.2.3
Requires-Dist: scikit-learn~=1.6.1
Requires-Dist: tqdm
Requires-Dist: ase~=3.24.0
Requires-Dist: spglib~=2.5.0
Requires-Dist: joblib
Dynamic: license-file
